pyDolarVenezuela/__init__.py
pyDolarVenezuela/exceptions.py
pyDolarVenezuela/models.py
pyDolarVenezuela/network.py
pyDolarVenezuela/pages.py
pyDolarVenezuela/provider.py
pyDolarVenezuela/storage.py
pyDolarVenezuela/version.py
pyDolarVenezuela/data/__init__.py
pyDolarVenezuela/data/engine.py
pyDolarVenezuela/data/main.py
pyDolarVenezuela/data/models.py
pyDolarVenezuela/providers/__init__.py
pyDolarVenezuela/providers/_base.py
pyDolarVenezuela/providers/alcambio.py
pyDolarVenezuela/providers/bcv.py
pyDolarVenezuela/providers/criptodolar.py
pyDolarVenezuela/providers/dolartoday.py
pyDolarVenezuela/providers/enparalelovzla.py
pyDolarVenezuela/providers/exchangemonitor.py
pyDolarVenezuela/providers/italcambio.py
pyDolarVenezuela/utils/__init__.py
pyDolarVenezuela/utils/calculator.py
pyDolarVenezuela/utils/common.py
pyDolarVenezuela/utils/extras.py
pyDolarVenezuela/utils/time.py
pyDolarVenezuela-2.0.2.dist-info/LICENSE
pyDolarVenezuela-2.0.2.dist-info/METADATA
pyDolarVenezuela-2.0.2.dist-info/WHEEL
pyDolarVenezuela-2.0.2.dist-info/top_level.txt
pyDolarVenezuela-2.0.2.dist-info/RECORD
