Metadata-Version: 2.1
Name: pyDolarVenezuela
Version: 2.0.2
Summary: Esta librería en Python consulta los precios del dólar y/o euro en diversos monitores en Venezuela, además de la tasa de cambio oficial BCV.
Home-page: https://github.com/fcoagz/pydolarvenezuela
Author: Francisco Griman
Author-email: Francisco Griman <grihardware@gmail.com>
License: Apache License
Project-URL: Homepage, https://github.com/fcoagz/pydolarvenezuela
Project-URL: Bug Tracker, https://github.com/fcoagz/pydolarvenezuela/issues
Keywords: dolarmonitor,dolartoday,enparalelovzla,bcv,venezuela,dolarparalelo,dolarcambio,dolarvenezuela,dolartodayvenezuela,dolaroficial,dolarlibre,dolarinformal,dolarparalelovzla,dolarbcv,dolarenvenezuela
Classifier: Programming Language :: Python :: 3.9
Classifier: Programming Language :: Python :: 3.10
Classifier: Programming Language :: Python :: 3.11
Classifier: License :: OSI Approved :: Apache Software License
Classifier: Operating System :: OS Independent
Requires-Python: >=3.9
License-File: LICENSE
Requires-Dist: requests
Requires-Dist: curl-cffi
Requires-Dist: beautifulsoup4
Requires-Dist: babel
Requires-Dist: pytz
Requires-Dist: colorama
Requires-Dist: cachetools
Requires-Dist: psycopg2-binary
Requires-Dist: sqlalchemy
